nubrain/__init__.py
nubrain/cli.py
nubrain/device/__init__.py
nubrain/device/device_interface.py
nubrain/example/__init__.py
nubrain/example/example.py
nubrain/experiment/__init__.py
nubrain/experiment/data.py
nubrain/experiment/example_config.yaml
nubrain/experiment/global_config.py
nubrain/experiment/load_config.py
nubrain/experiment/main.py
nubrain/experiment/randomize_conditions.py
nubrain/experiment_eeg_to_image_v1/__init__.py
nubrain/experiment_eeg_to_image_v1/example_config.yaml
nubrain/experiment_eeg_to_image_v1/load_config.py
nubrain/experiment_eeg_to_image_v1/main.py
nubrain/experiment_eeg_to_image_v1/main_autoregressive.py
nubrain/experiment_eeg_to_image_v1/tone.py
nubrain/image/__init__.py
nubrain/image/tools.py
nubrain/misc/__init__.py
nubrain/misc/datetime.py
nubrain-0.1.37.dist-info/METADATA
nubrain-0.1.37.dist-info/WHEEL
nubrain-0.1.37.dist-info/entry_points.txt
nubrain-0.1.37.dist-info/RECORD
