Metadata-Version: 2.4
Name: nubrain
Version: 0.1.37
Summary: NuBrain connect
Project-URL: Homepage, https://nubrain.io/
Author-email: nuBrain Team <hello@nubrain.io>
License-Expression: MIT
Requires-Python: >=3.10
Requires-Dist: brainflow>=5.16.0
Requires-Dist: certifi>=2025.4.26
Requires-Dist: charset-normalizer>=3.4.2
Requires-Dist: h5py
Requires-Dist: idna>=3.10
Requires-Dist: numpy>=2.2.6
Requires-Dist: pillow>=11.2.1
Requires-Dist: pygame>=2.6.1
Requires-Dist: pylsl>=1.17.6
Requires-Dist: pyyaml
Requires-Dist: requests>=2.32.3
Requires-Dist: scipy>=1.15.3
Requires-Dist: urllib3>=2.4.0
Requires-Dist: websockets>=15.0.1
Provides-Extra: dev
Requires-Dist: build; extra == 'dev'
Requires-Dist: spyder-kernels==2.5.2; extra == 'dev'
Requires-Dist: twine; extra == 'dev'
